shucks.py
shucks/__init__.py
shucks/checks.py
shucks/helpers.py
shucks/schema.py
shucks-1.2.1.dist-info/LICENCE
shucks-1.2.1.dist-info/METADATA
shucks-1.2.1.dist-info/WHEEL
shucks-1.2.1.dist-info/top_level.txt
shucks-1.2.1.dist-info/RECORD
