Metadata-Version: 2.1
Name: shucks
Version: 1.2.1
Summary: Quick schema validator.
Home-page: https://github.com/Exahilosys/shucks
Author: Exahilosys
Author-email: UNKNOWN
License: MIT
Platform: UNKNOWN
